Workbook

Sheet Startup Cost
B3: Startup Cost
B8: Tool | G8: Lisence
B10: ITEM NAME | C10: QUANTITY | D10: UNIT PRICE | E10: TOTAL | G10: ITEM NAME | H10: QUANTITY | I10: UNIT PRICE | J10: TOTAL
B11: kipas | C11: 1 | D11: 300000 | E11: =SUM(C11*D11*$D$24) -> 300000 | G11: Dapur | H11: 1 | I11: 3000000 | J11: =SUM(H11*I11*$D$24) -> 3000000
B12: sarung tangan | C12: 1 | D12: 100000 | E12: =SUM(C12*D12*$D$24) -> 100000 | G12: Listrik | H12: 1 | I12: 1000000 | J12: =SUM(H12*I12*$D$24) -> 1000000
B13: wastafel | C13: 1 | D13: 300000 | E13: =SUM(C13*D13*$D$24) -> 300000 | I13: Total : | J13: =SUM(J11:J12) -> 4000000
B14: kuali | C14: 1 | D14: 200000 | E14: =SUM(C14*D14*$D$24) -> 200000
B15: panci | C15: 1 | D15: 200000 | E15: =SUM(C15*D15*$D$24) -> 200000
B16: pisau | C16: 2 | D16: 100000 | E16: =SUM(C16*D16*$D$24) -> 200000
B17: alas pisau | C17: 2 | D17: 50000 | E17: =SUM(C17*D17*$D$24) -> 100000
B18: kompor | C18: 1 | D18: 150000 | E18: =SUM(C18*D18*$D$24) -> 150000
B19: alat masak | C19: 1 | D19: 500000 | E19: =SUM(C19*D19*$D$24) -> 500000
B20: meja | C20: 1 | D20: 100000 | E20: =SUM(C20*D20*$D$24) -> 100000
D21: Total : | E21: =SUM(E11:E20) -> 2150000
B24: Total Cabang : | D24: 1
B25: Total Biaya : | D25: =E21+J13 -> 6150000

Sheet Expense Forecast
B8: Expense Forecast
B11: Month | C11: Expense ForeCast
C12: Cooking Staff | D12: Cooking Staff | E12: Admin Kitchen | F12: Ingredient
B13: 1 | C13: =J16 -> 2000000 | D13: =J16 -> 2000000 | E13: =K16 -> 1500000 | F13: =L16 -> 6000000 | G13: =SUM(C13:F13) -> 11500000 | I13: Sys
B14: 2 | C14: =J16+J17 -> 2015000 | D14: =J16+J17 -> 2015000 | E14: =K16+K17 -> 1505000 | F14: =L16+L17 -> 8000000 | G14: =SUM(C14:F14) -> 13535000
B15: 3 | C15: =FORECAST($B15,C$13:C14,$B$13:$B14) -> 2030000 | D15: =FORECAST($B15,D$13:D14,$B$13:$B14) -> 2030000 | E15: =FORECAST($B15,E$13:E14,$B$13:$B14) -> 1510000 | F15: =FORECAST($B15,F$13:F14,$B$13:$B14) -> 10000000 | G15: =SUM(C15:F15) -> 15570000 | J15: Cooking Saff | K15: Admin Kitchen | L15: Ingridient
B16: 4 | C16: =FORECAST($B16,C$13:C15,$B$13:$B15) -> 2045000 | D16: =FORECAST($B16,D$13:D15,$B$13:$B15) -> 2045000 | E16: =FORECAST($B16,E$13:E15,$B$13:$B15) -> 1515000 | F16: =FORECAST($B16,F$13:F15,$B$13:$B15) -> 12000000 | G16: =SUM(C16:F16) -> 17605000 | I16: Based | J16: 2000000 | K16: 1500000 | L16: 6000000
B17: 5 | C17: =FORECAST($B17,C$13:C16,$B$13:$B16) -> 2060000 | D17: =FORECAST($B17,D$13:D16,$B$13:$B16) -> 2060000 | E17: =FORECAST($B17,E$13:E16,$B$13:$B16) -> 1520000 | F17: =FORECAST($B17,F$13:F16,$B$13:$B16) -> 14000000 | G17: =SUM(C17:F17) -> 19640000 | I17: Increasement | J17: 15000 | K17: 5000 | L17: 2000000
B18: 6 | C18: =FORECAST($B18,C$13:C17,$B$13:$B17) -> 2075000 | D18: =FORECAST($B18,D$13:D17,$B$13:$B17) -> 2075000 | E18: =FORECAST($B18,E$13:E17,$B$13:$B17) -> 1525000 | F18: =FORECAST($B18,F$13:F17,$B$13:$B17) -> 16000000 | G18: =SUM(C18:F18) -> 21675000
B19: 7 | C19: =FORECAST($B19,C$13:C18,$B$13:$B18) -> 2090000 | D19: =FORECAST($B19,D$13:D18,$B$13:$B18) -> 2090000 | E19: =FORECAST($B19,E$13:E18,$B$13:$B18) -> 1530000 | F19: =FORECAST($B19,F$13:F18,$B$13:$B18) -> 18000000 | G19: =SUM(C19:F19) -> 23710000
B20: 8 | C20: =FORECAST($B20,C$13:C19,$B$13:$B19) -> 2105000 | D20: =FORECAST($B20,D$13:D19,$B$13:$B19) -> 2105000 | E20: =FORECAST($B20,E$13:E19,$B$13:$B19) -> 1535000 | F20: =FORECAST($B20,F$13:F19,$B$13:$B19) -> 20000000 | G20: =SUM(C20:F20) -> 25745000
B21: 9 | C21: =FORECAST($B21,C$13:C20,$B$13:$B20) -> 2120000 | D21: =FORECAST($B21,D$13:D20,$B$13:$B20) -> 2120000 | E21: =FORECAST($B21,E$13:E20,$B$13:$B20) -> 1540000 | F21: =FORECAST($B21,F$13:F20,$B$13:$B20) -> 22000000 | G21: =SUM(C21:F21) -> 27780000
B22: 10 | C22: =FORECAST($B22,C$13:C21,$B$13:$B21) -> 2135000 | D22: =FORECAST($B22,D$13:D21,$B$13:$B21) -> 2135000 | E22: =FORECAST($B22,E$13:E21,$B$13:$B21) -> 1545000 | F22: =FORECAST($B22,F$13:F21,$B$13:$B21) -> 24000000 | G22: =SUM(C22:F22) -> 29815000
B23: 11 | C23: =FORECAST($B23,C$13:C22,$B$13:$B22) -> 2150000 | D23: =FORECAST($B23,D$13:D22,$B$13:$B22) -> 2150000 | E23: =FORECAST($B23,E$13:E22,$B$13:$B22) -> 1550000 | F23: =FORECAST($B23,F$13:F22,$B$13:$B22) -> 26000000 | G23: =SUM(C23:F23) -> 31850000
B24: 12 | C24: =FORECAST($B24,C$13:C23,$B$13:$B23) -> 2165000 | D24: =FORECAST($B24,D$13:D23,$B$13:$B23) -> 2165000 | E24: =FORECAST($B24,E$13:E23,$B$13:$B23) -> 1555000 | F24: =FORECAST($B24,F$13:F23,$B$13:$B23) -> 28000000 | G24: =SUM(C24:F24) -> 33885000
B27: Total : | C27: =SUM(C13:C24) -> 24990000 | D27: =SUM(D13:D24) -> 24990000 | E27: =SUM(E13:E24) -> 18330000 | F27: =SUM(F13:F24) -> 204000000
B28: Total : | C28: =SUM(C27:F27) -> 272310000

Sheet Sales Forecast
B8: Sales ForeCast
B11: Month | C11: Unit Sold | H11: Price Per unit | M11: Revenue
C12: Monthly Pass | D12: Weekly Pass | E12: Vegetarian Meals | F12: Healthy Meals | G12: Beast Meals | H12: Monthly Pass | I12: Weekly Pass | J12: Vegetarian Meals | K12: Healthy Meals | L12: Beast Meals | M12: Monthly Pass | N12: Weekly Pass | O12: Vegetarian Meals | P12: Healthy Meals | Q12: Beast Meals
B13: 1 | C13: 5 | D13: 1 | E13: 160 | F13: 5 | G13: 10 | H13: 650000 | I13: 200000 | J13: 30000 | K13: 50000 | L13: 25000 | M13: =SUM(C13*H13) -> 3250000 | N13: =SUM(D13*I13) -> 200000 | O13: =SUM(E13*J13) -> 4800000 | P13: =SUM(F13*K13) -> 250000 | Q13: =SUM(G13*L13) -> 250000 | R13: =SUM(M13:Q13) -> 8750000
B14: 2 | C14: 10 | D14: 2 | E14: 180 | F14: 6 | G14: 20 | H14: 650000 | I14: 200000 | J14: 30000 | K14: 50000 | L14: 25000 | M14: =SUM(C14*H14) -> 6500000 | N14: =SUM(D14*I14) -> 400000 | O14: =SUM(E14*J14) -> 5400000 | P14: =SUM(F14*K14) -> 300000 | Q14: =SUM(G14*L14) -> 500000 | R14: =SUM(M14:Q14) -> 13100000
B15: 3 | C15: =FORECAST($B15,C$13:C14,$B$13:$B14) -> 15 | D15: =FORECAST($B15,D$13:D14,$B$13:$B14) -> 3 | E15: =FORECAST($B15,E$13:E14,$B$13:$B14) -> 200 | F15: =FORECAST($B15,F$13:F14,$B$13:$B14) -> 7 | G15: =FORECAST($B15,G$13:G14,$B$13:$B14) -> 30 | H15: 650000 | I15: 200000 | J15: 30000 | K15: 50000 | L15: 25000 | M15: =SUM(C15*H15) -> 9750000 | N15: =SUM(D15*I15) -> 600000 | O15: =SUM(E15*J15) -> 6000000 | P15: =SUM(F15*K15) -> 350000 | Q15: =SUM(G15*L15) -> 750000 | R15: =SUM(M15:Q15) -> 17450000
B16: 4 | C16: =FORECAST($B16,C$13:C15,$B$13:$B15) -> 20 | D16: =FORECAST($B16,D$13:D15,$B$13:$B15) -> 4 | E16: =FORECAST($B16,E$13:E15,$B$13:$B15) -> 220 | F16: =FORECAST($B16,F$13:F15,$B$13:$B15) -> 8 | G16: =FORECAST($B16,G$13:G15,$B$13:$B15) -> 40 | H16: 650000 | I16: 200000 | J16: 30000 | K16: 50000 | L16: 25000 | M16: =SUM(C16*H16) -> 13000000 | N16: =SUM(D16*I16) -> 800000 | O16: =SUM(E16*J16) -> 6600000 | P16: =SUM(F16*K16) -> 400000 | Q16: =SUM(G16*L16) -> 1000000 | R16: =SUM(M16:Q16) -> 21800000
B17: 5 | C17: =FORECAST($B17,C$13:C16,$B$13:$B16) -> 25 | D17: =FORECAST($B17,D$13:D16,$B$13:$B16) -> 5 | E17: =FORECAST($B17,E$13:E16,$B$13:$B16) -> 240 | F17: =FORECAST($B17,F$13:F16,$B$13:$B16) -> 9 | G17: =FORECAST($B17,G$13:G16,$B$13:$B16) -> 50 | H17: 650000 | I17: 200000 | J17: 30000 | K17: 50000 | L17: 25000 | M17: =SUM(C17*H17) -> 16250000 | N17: =SUM(D17*I17) -> 1000000 | O17: =SUM(E17*J17) -> 7200000 | P17: =SUM(F17*K17) -> 450000 | Q17: =SUM(G17*L17) -> 1250000 | R17: =SUM(M17:Q17) -> 26150000
B18: 6 | C18: =FORECAST($B18,C$13:C17,$B$13:$B17) -> 30 | D18: =FORECAST($B18,D$13:D17,$B$13:$B17) -> 6 | E18: =FORECAST($B18,E$13:E17,$B$13:$B17) -> 260 | F18: =FORECAST($B18,F$13:F17,$B$13:$B17) -> 10 | G18: =FORECAST($B18,G$13:G17,$B$13:$B17) -> 60 | H18: 650000 | I18: 200000 | J18: 30000 | K18: 50000 | L18: 25000 | M18: =SUM(C18*H18) -> 19500000 | N18: =SUM(D18*I18) -> 1200000 | O18: =SUM(E18*J18) -> 7800000 | P18: =SUM(F18*K18) -> 500000 | Q18: =SUM(G18*L18) -> 1500000 | R18: =SUM(M18:Q18) -> 30500000
B19: 7 | C19: =FORECAST($B19,C$13:C18,$B$13:$B18) -> 35 | D19: =FORECAST($B19,D$13:D18,$B$13:$B18) -> 7 | E19: =FORECAST($B19,E$13:E18,$B$13:$B18) -> 280 | F19: =FORECAST($B19,F$13:F18,$B$13:$B18) -> 11 | G19: =FORECAST($B19,G$13:G18,$B$13:$B18) -> 70 | H19: 650000 | I19: 200000 | J19: 30000 | K19: 50000 | L19: 25000 | M19: =SUM(C19*H19) -> 22750000 | N19: =SUM(D19*I19) -> 1400000 | O19: =SUM(E19*J19) -> 8400000 | P19: =SUM(F19*K19) -> 550000 | Q19: =SUM(G19*L19) -> 1750000 | R19: =SUM(M19:Q19) -> 34850000
B20: 8 | C20: =FORECAST($B20,C$13:C19,$B$13:$B19) -> 40 | D20: =FORECAST($B20,D$13:D19,$B$13:$B19) -> 8 | E20: =FORECAST($B20,E$13:E19,$B$13:$B19) -> 300 | F20: =FORECAST($B20,F$13:F19,$B$13:$B19) -> 12 | G20: =FORECAST($B20,G$13:G19,$B$13:$B19) -> 80 | H20: 650000 | I20: 200000 | J20: 30000 | K20: 50000 | L20: 25000 | M20: =SUM(C20*H20) -> 26000000 | N20: =SUM(D20*I20) -> 1600000 | O20: =SUM(E20*J20) -> 9000000 | P20: =SUM(F20*K20) -> 600000 | Q20: =SUM(G20*L20) -> 2000000 | R20: =SUM(M20:Q20) -> 39200000
B21: 9 | C21: =FORECAST($B21,C$13:C20,$B$13:$B20) -> 45 | D21: =FORECAST($B21,D$13:D20,$B$13:$B20) -> 9 | E21: =FORECAST($B21,E$13:E20,$B$13:$B20) -> 320 | F21: =FORECAST($B21,F$13:F20,$B$13:$B20) -> 13 | G21: =FORECAST($B21,G$13:G20,$B$13:$B20) -> 90 | H21: 650000 | I21: 200000 | J21: 30000 | K21: 50000 | L21: 25000 | M21: =SUM(C21*H21) -> 29250000 | N21: =SUM(D21*I21) -> 1800000 | O21: =SUM(E21*J21) -> 9600000 | P21: =SUM(F21*K21) -> 650000 | Q21: =SUM(G21*L21) -> 2250000 | R21: =SUM(M21:Q21) -> 43550000
B22: 10 | C22: =FORECAST($B22,C$13:C21,$B$13:$B21) -> 50 | D22: =FORECAST($B22,D$13:D21,$B$13:$B21) -> 10 | E22: =FORECAST($B22,E$13:E21,$B$13:$B21) -> 340 | F22: =FORECAST($B22,F$13:F21,$B$13:$B21) -> 14 | G22: =FORECAST($B22,G$13:G21,$B$13:$B21) -> 100 | H22: 650000 | I22: 200000 | J22: 30000 | K22: 50000 | L22: 25000 | M22: =SUM(C22*H22) -> 32500000 | N22: =SUM(D22*I22) -> 2000000 | O22: =SUM(E22*J22) -> 10200000 | P22: =SUM(F22*K22) -> 700000 | Q22: =SUM(G22*L22) -> 2500000 | R22: =SUM(M22:Q22) -> 47900000
B23: 11 | C23: =FORECAST($B23,C$13:C22,$B$13:$B22) -> 55 | D23: =FORECAST($B23,D$13:D22,$B$13:$B22) -> 11 | E23: =FORECAST($B23,E$13:E22,$B$13:$B22) -> 360 | F23: =FORECAST($B23,F$13:F22,$B$13:$B22) -> 15 | G23: =FORECAST($B23,G$13:G22,$B$13:$B22) -> 110 | H23: 650000 | I23: 200000 | J23: 30000 | K23: 50000 | L23: 25000 | M23: =SUM(C23*H23) -> 35750000 | N23: =SUM(D23*I23) -> 2200000 | O23: =SUM(E23*J23) -> 10800000 | P23: =SUM(F23*K23) -> 750000 | Q23: =SUM(G23*L23) -> 2750000 | R23: =SUM(M23:Q23) -> 52250000
B24: 12 | C24: =FORECAST($B24,C$13:C23,$B$13:$B23) -> 60 | D24: =FORECAST($B24,D$13:D23,$B$13:$B23) -> 12 | E24: =FORECAST($B24,E$13:E23,$B$13:$B23) -> 380 | F24: =FORECAST($B24,F$13:F23,$B$13:$B23) -> 16 | G24: =FORECAST($B24,G$13:G23,$B$13:$B23) -> 120 | H24: 650000 | I24: 200000 | J24: 30000 | K24: 50000 | L24: 25000 | M24: =SUM(C24*H24) -> 39000000 | N24: =SUM(D24*I24) -> 2400000 | O24: =SUM(E24*J24) -> 11400000 | P24: =SUM(F24*K24) -> 800000 | Q24: =SUM(G24*L24) -> 3000000 | R24: =SUM(M24:Q24) -> 56600000
M32: Monthly Pass | N32: Weekly Pass | O32: Vegetarian Meals | P32: Healthy Meals | Q32: Beast Meals
L33: Total : | M33: =SUM(M$13:M$31) -> 253500000 | N33: =SUM(N$13:N$31) -> 15600000 | O33: =SUM(O$13:O$31) -> 97200000 | P33: =SUM(P$13:P$31) -> 6300000 | Q33: =SUM(Q$13:Q$31) -> 19500000
L34: Total : | M34: =SUM(M33:Q33) -> 392100000

Sheet Profit & Loss Projection
C5: Profit Data
C8: Month | D8: Revenue | E8: Expenses | F8: Net Profit
C9: 1 | D9: ='Sales Forecast'!R13 -> 8750000 | E9: ='Expense Forecast'!G13 -> 11500000 | F9: =SUM(D9-E9)-'Startup Cost'!D25 -> -8900000
C10: 2 | D10: ='Sales Forecast'!R14 -> 13100000 | E10: ='Expense Forecast'!G14 -> 13535000 | F10: =SUM(D10-E10)-'Startup Cost'!$J$13 -> -4435000
C11: 3 | D11: ='Sales Forecast'!R15 -> 17450000 | E11: ='Expense Forecast'!G15 -> 15570000 | F11: =SUM(D11-E11)-'Startup Cost'!$J$13 -> -2120000
C12: 4 | D12: ='Sales Forecast'!R16 -> 21800000 | E12: ='Expense Forecast'!G16 -> 17605000 | F12: =SUM(D12-E12)-'Startup Cost'!$J$13 -> 195000
C13: 5 | D13: ='Sales Forecast'!R17 -> 26150000 | E13: ='Expense Forecast'!G17 -> 19640000 | F13: =SUM(D13-E13)-'Startup Cost'!$J$13 -> 2510000
C14: 6 | D14: ='Sales Forecast'!R18 -> 30500000 | E14: ='Expense Forecast'!G18 -> 21675000 | F14: =SUM(D14-E14)-'Startup Cost'!$J$13 -> 4825000
C15: 7 | D15: ='Sales Forecast'!R19 -> 34850000 | E15: ='Expense Forecast'!G19 -> 23710000 | F15: =SUM(D15-E15)-'Startup Cost'!D25 -> 4990000
C16: 8 | D16: ='Sales Forecast'!R20 -> 39200000 | E16: ='Expense Forecast'!G20 -> 25745000 | F16: =SUM(D16-E16)-'Startup Cost'!$J$13 -> 9455000
C17: 9 | D17: ='Sales Forecast'!R21 -> 43550000 | E17: ='Expense Forecast'!G21 -> 27780000 | F17: =SUM(D17-E17)-'Startup Cost'!$J$13 -> 11770000
C18: 10 | D18: ='Sales Forecast'!R22 -> 47900000 | E18: ='Expense Forecast'!G22 -> 29815000 | F18: =SUM(D18-E18)-'Startup Cost'!$J$13 -> 14085000
C19: 11 | D19: ='Sales Forecast'!R23 -> 52250000 | E19: ='Expense Forecast'!G23 -> 31850000 | F19: =SUM(D19-E19)-'Startup Cost'!$J$13 -> 16400000
C20: 12 | D20: ='Sales Forecast'!R24 -> 56600000 | E20: ='Expense Forecast'!G24 -> 33885000 | F20: =SUM(D20-E20)-'Startup Cost'!$J$13 -> 18715000
E22: Total : | F22: =SUM(F9:F20) -> 67490000

Sheet Break-even Analysis

Sheet Calculation Cooking Ingredient
E5: Calculation Cooking Ingredient
D9: NO. | E9: Ingredients | F9: Amount (kg) | G9: Price (kg) | H9: Total | K9: NO. | L9: Ingredients | M9: Amount (kg) | N9: Price (kg) | O9: Total
D10: 1 | E10: Tomato | F10: 5 | G10: 4500 | H10: =G10*F10 -> 22500 | K10: 26 | L10: Tomato Sauce | O10: =N10*M10 -> 0
D11: 2 | E11: Broccoli | F11: 1 | G11: 24000 | H11: =G11*F11 -> 24000 | K11: 27 | L11: Chilli Sauce | O11: =N11*M11 -> 0
D12: 3 | E12: Chilli | F12: 1 | G12: 15500 | H12: =G12*F12 -> 15500 | K12: 28 | L12: Cheese | O12: =N12*M12 -> 0
D13: 4 | E13: Potato | F13: 1 | G13: 7000 | H13: =G13*F13 -> 7000 | K13: 29 | L13: Oat | O13: =N13*M13 -> 0
D14: 5 | E14: Egg | F14: 3 | G14: 12000 | H14: =G14*F14 -> 36000 | K14: 30 | L14: Tortilla Shell | O14: =N14*M14 -> 0
D15: 6 | E15: Garlic | F15: 1 | G15: 4000 | H15: =G15*F15 -> 4000 | K15: 31 | L15: Roasted Sesame Mayonnaise | O15: =N15*M15 -> 0
D16: 7 | E16: Red Onion | F16: 1 | G16: 4000 | H16: =G16*F16 -> 4000 | K16: 32 | L16: Oyster Mushroom | O16: =N16*M16 -> 0
D17: 8 | E17: Cucumber | F17: 1 | G17: 3000 | H17: =G17*F17 -> 3000 | K17: 33 | L17: Tofu | O17: =N17*M17 -> 0
D18: 9 | E18: Parsley Leaves | H18: =G18*F18 -> 0 | K18: 34 | L18: Avocado | O18: =N18*M18 -> 0
D19: 10 | E19: Soup Leaves | F19: 1 | G19: 5000 | H19: =G19*F19 -> 5000 | K19: 35 | L19: Strawberry | O19: =N19*M19 -> 0
D20: 11 | E20: Lettuce | H20: =G20*F20 -> 0 | K20: 36 | L20: Oyster Sauce | O20: =N20*M20 -> 0
D21: 12 | E21: Carrot | F21: 1 | G21: 7000 | H21: =G21*F21 -> 7000 | K21: 37 | L21: Mushroom Broth | O21: =N21*M21 -> 0
D22: 13 | E22: Purple Cabbage | H22: =G22*F22 -> 0 | K22: 38 | L22: Cooking Oil | O22: =N22*M22 -> 0
D23: 14 | E23: Corn | F23: 5 | G23: 7000 | H23: =G23*F23 -> 35000 | K23: 39 | L23: Peanut Sauce | O23: =N23*M23 -> 0
D24: 15 | E24: Beef | H24: =G24*F24 -> 0 | K24: 40 | L24: Salt | O24: =N24*M24 -> 0
D25: 16 | E25: Long Beans | H25: =G25*F25 -> 0 | K25: 41 | L25: Fish | O25: =N25*M25 -> 0
D26: 17 | E26: Mustard leaves | H26: =G26*F26 -> 0 | K26: 42 | L26: Green Tea | O26: =N26*M26 -> 0
D27: 18 | E27: Mayonnaise | H27: =G27*F27 -> 0 | K27: 43 | L27: Vegetable Oil | O27: =N27*M27 -> 0
D28: 19 | E28: Sesame Oil | H28: =G28*F28 -> 0 | K28: 44 | L28: Tempe | O28: =N28*M28 -> 0
D29: 20 | E29: Mustard | H29: =G29*F29 -> 0 | K29: 45 | L29: Milk | O29: =N29*M29 -> 0
D30: 21 | E30: Turmeric | H30: =G30*F30 -> 0 | K30: 46 | L30: Butter | O30: =N30*M30 -> 0
D31: 22 | E31: Ginger | H31: =G31*F31 -> 0 | K31: 47 | L31: Spinach | O31: =N31*M31 -> 0
D32: 23 | E32: Galangal | H32: =G32*F32 -> 0 | K32: 48 | L32: Paprika | O32: =N32*M32 -> 0
D33: 24 | E33: Sesame Seeds | H33: =G33*F33 -> 0 | K33: 49 | L33: Peas | O33: =N33*M33 -> 0
D34: 25 | E34: Seaweed | H34: =G34*F34 -> 0 | K34: 50 | L34: Almond | O34: =N34*M34 -> 0
